pixi_sync_environment/__init__.py
pixi_sync_environment/cli.py
pixi_sync_environment/io.py
pixi_sync_environment/package_info.py
pixi_sync_environment/pixi_environment.py
pixi_sync_environment-0.2.0.dist-info/WHEEL
pixi_sync_environment-0.2.0.dist-info/entry_points.txt
pixi_sync_environment-0.2.0.dist-info/METADATA
pixi_sync_environment-0.2.0.dist-info/RECORD
