Metadata-Version: 2.3
Name: pixi-sync-environment
Version: 0.2.0
Summary: Pre-commit hook to sync a pixi environment with a traditional conda environment.yml
Keywords: 
Author: Bernardo Veronese
Author-email: Bernardo Veronese <bernardopveronese@gmail.com>
License: MIT License
Classifier: Programming Language :: Python :: 3
Requires-Dist: pyyaml>=6.0.2
Requires-Python: >=3.10
Project-URL: Homepage, https://github.com/binado/pixi-sync-environment
